odoo/addons/shopinvader_product_media/README.rst
odoo/addons/shopinvader_product_media/__init__.py
odoo/addons/shopinvader_product_media/__manifest__.py
odoo/addons/shopinvader_product_media/data/ir_product_export.xml
odoo/addons/shopinvader_product_media/i18n/shopinvader_product_media.pot
odoo14_addon_shopinvader_product_media-14.0.1.1.0.dist-info/METADATA
odoo14_addon_shopinvader_product_media-14.0.1.1.0.dist-info/WHEEL
odoo14_addon_shopinvader_product_media-14.0.1.1.0.dist-info/top_level.txt
odoo14_addon_shopinvader_product_media-14.0.1.1.0.dist-info/RECORD
